.travis.yml
CHANGES.rst
CONTRIBUTORS.rst
README.rst
bootstrap.py
buildout.cfg
setup.cfg
setup.py
travis.cfg
docs/LICENSE.GPL
docs/LICENSE.txt
src/collective/__init__.py
src/collective.clipboardupload.egg-info/PKG-INFO
src/collective.clipboardupload.egg-info/SOURCES.txt
src/collective.clipboardupload.egg-info/dependency_links.txt
src/collective.clipboardupload.egg-info/entry_points.txt
src/collective.clipboardupload.egg-info/namespace_packages.txt
src/collective.clipboardupload.egg-info/not-zip-safe
src/collective.clipboardupload.egg-info/paster_plugins.txt
src/collective.clipboardupload.egg-info/requires.txt
src/collective.clipboardupload.egg-info/top_level.txt
src/collective/clipboardupload/__init__.py
src/collective/clipboardupload/configure.zcml
src/collective/clipboardupload/imageupload.py
src/collective/clipboardupload/testing.py
src/collective/clipboardupload/testing.zcml
src/collective/clipboardupload/tests/__init__.py
src/collective/clipboardupload/tests/test_doctests.py
src/collective/clipboardupload/tests/test_robot.py
src/collective/clipboardupload/tests/robot/owl.jpg.base64
src/collective/clipboardupload/tests/robot/test_paste_image.robot