Metadata-Version: 1.0
Name: collective.clipboardupload
Version: 1.0
Summary: Allows uploading images into Plone site by pasting them into TinyMCE WYSIWYG editor
Home-page: https://github.com/quintagroup/collective.clipboardupload
Author: Quintagroup
Author-email: support@quintagroup.com
License: gpl
Keywords: Zope CMF Plone Clipboard Upload
Platform: UNKNOWN
Classifier: Framework :: Plone
Classifier: Framework :: Plone :: 4.0
Classifier: Framework :: Plone :: 4.1
Classifier: Framework :: Plone :: 4.2
Classifier: Framework :: Zope2
Classifier: Framework :: Zope3
Classifier: Environment :: Web Environment
Classifier: Operating System :: OS Independent
Classifier: Programming Language :: Python
Classifier: Programming Language :: Python :: 2.6
Classifier: Programming Language :: Python :: 2.7
Classifier: Topic :: Software Development :: Libraries :: Python Modules
Classifier: License :: OSI Approved :: GNU General Public License (GPL)
